{
    "global": {
        "id": "7293284592491023135",
        "img": "https://tokchart.com/img/7293284592491023135/600",
        "author": "Jack Harlow",
        "title": "Lovin On Me",
        "growing_number": "+21K",
        "tiktok_url": "https://www.tiktok.com/music/lovin-on-me-7293284592491023135"
    },
    "growing": {
        "id": "7298430097618503682",
        "img": "https://tokchart.com/img/7298430097618503682/600",
        "author": "David Guetta & Kim Petras",
        "title": "When We Were Young (The Logical Song)",
        "growing_number": "+4K",
        "tiktok_url": "https://www.tiktok.com/music/when-we-were-young-the-logical-song-7298430097618503682"
    },
    "countries": {
        "spain": [
            {
                "id": "6976753048529930242",
                "img": "https://tokchart.com/img/6976753048529930242/600",
                "author": "Lola Indigo & TINI & Belinda",
                "title": "La Niña de la Escuela",
                "tiktok_url": "https://www.tiktok.com/music/la-nina-de-la-escuela-6976753048529930242"
            },
            {
                "id": "6967073900530239489",
                "img": "https://tokchart.com/img/6967073900530239489/600",
                "author": "Rocco Hunt & Ana Mena",
                "title": "Un bacio all'improvviso",
                "tiktok_url": "https://www.tiktok.com/music/un-bacio-allimprovviso-6967073900530239489"
            },
            {
                "id": "6754595656993605633",
                "img": "https://tokchart.com/img/6754595656993605633/600",
                "author": "Justin Wellington",
                "title": "Iko Iko (My Bestie) (feat. Small Jam)",
                "tiktok_url": "https://www.tiktok.com/music/iko-iko-my-bestie-feat-small-jam-6754595656993605633"
            },
            {
                "id": "6935505953866156033",
                "img": "https://tokchart.com/img/6935505953866156033/600",
                "author": "Måneskin",
                "title": "I WANNA BE YOUR SLAVE",
                "tiktok_url": "https://www.tiktok.com/music/i-wanna-be-your-slave-6935505953866156033"
            },
            {
                "id": "6844610572080794373",
                "img": "https://tokchart.com/img/6844610572080794373/600",
                "author": "Fleetwood Mac",
                "title": "Dreams (2004 Remaster)",
                "tiktok_url": "https://www.tiktok.com/music/dreams-2004-remaster-6844610572080794373"
            },
            {
                "id": "7008904819305876229",
                "img": "https://tokchart.com/img/7008904819305876229/200",
                "author": "Els Catarres",
                "title": "Jenifer",
                "tiktok_url": "https://www.tiktok.com/music/jenifer-7008904819305876229"
            },
            {
                "id": "7049789820666660865",
                "img": "https://tokchart.com/img/7049789820666660865/200",
                "author": "Funzo & Baby Loud",
                "title": "TO' BUENA VIBRA (pre-release)",
                "tiktok_url": "https://www.tiktok.com/music/to-buena-vibra-pre-release-7049789820666660865"
            },
            {
                "id": "6896646325899626498",
                "img": "https://tokchart.com/img/6896646325899626498/200",
                "author": "Yan Block & Jay Wheeler & DJ Nelson",
                "title": "Vete Pal Carajo",
                "tiktok_url": "https://www.tiktok.com/music/vete-pal-carajo-6896646325899626498"
            },
            {
                "id": "6997044305127573505",
                "img": "https://tokchart.com/img/6997044305127573505/200",
                "author": "zzoilo & Aitana",
                "title": "Mon Amour - Remix",
                "tiktok_url": "https://www.tiktok.com/music/mon-amour-remix-6997044305127573505"
            },
            {
                "id": "6936178645819983874",
                "img": "https://tokchart.com/img/6936178645819983874/200",
                "author": "Chema Rivas & Juan Magán",
                "title": "Anda Suelta",
                "tiktok_url": "https://www.tiktok.com/music/anda-suelta-6936178645819983874"
            }
        ],
        "usa": [
            {
                "id": "6844610572080794373",
                "img": "https://tokchart.com/img/6844610572080794373/600",
                "author": "Fleetwood Mac",
                "title": "Dreams (2004 Remaster)",
                "tiktok_url": "https://www.tiktok.com/music/dreams-2004-remaster-6844610572080794373"
            },
            {
                "id": "6896128359923714049",
                "img": "https://tokchart.com/img/6896128359923714049/600",
                "author": "Miley Cyrus",
                "title": "Prisoner (feat. Dua Lipa)",
                "tiktok_url": "https://www.tiktok.com/music/prisoner-feat-dua-lipa-6896128359923714049"
            },
            {
                "id": "6878744350931634950",
                "img": "https://tokchart.com/img/6878744350931634950/600",
                "author": "松原みき",
                "title": "真夜中のドア〜stay with me",
                "tiktok_url": "https://www.tiktok.com/music/stay-with-me-6878744350931634950"
            },
            {
                "id": "6911688776167312134",
                "img": "https://tokchart.com/img/6911688776167312134/600",
                "author": "Gipsy Kings",
                "title": "Bamboleo",
                "tiktok_url": "https://www.tiktok.com/music/bamboleo-6911688776167312134"
            },
            {
                "id": "6878440054709028865",
                "img": "https://tokchart.com/img/6878440054709028865/600",
                "author": "Shawn Mendes",
                "title": "Wonder",
                "tiktok_url": "https://www.tiktok.com/music/wonder-6878440054709028865"
            },
            {
                "id": "227302284517642240",
                "img": "https://tokchart.com/img/227302284517642240/200",
                "author": "Grover Washington, Jr.",
                "title": "Just the Two of Us",
                "tiktok_url": "https://www.tiktok.com/music/just-the-two-of-us-227302284517642240"
            },
            {
                "id": "6914711053674760193",
                "img": "https://tokchart.com/img/6914711053674760193/200",
                "author": "Olivia Rodrigo",
                "title": "drivers license",
                "tiktok_url": "https://www.tiktok.com/music/drivers-license-6914711053674760193"
            },
            {
                "id": "6894066988063131649",
                "img": "https://tokchart.com/img/6894066988063131649/200",
                "author": "Billie Eilish",
                "title": "Therefore I Am",
                "tiktok_url": "https://www.tiktok.com/music/therefore-i-am-6894066988063131649"
            },
            {
                "id": "6740248251825391617",
                "img": "https://tokchart.com/img/6740248251825391617/200",
                "author": "Labrinth",
                "title": "Forever",
                "tiktok_url": "https://www.tiktok.com/music/forever-6740248251825391617"
            },
            {
                "id": "6889276181086996481",
                "img": "https://tokchart.com/img/6889276181086996481/200",
                "author": "Ariana Grande",
                "title": "pov",
                "tiktok_url": "https://www.tiktok.com/music/pov-6889276181086996481"
            }
        ],
        "uk": [
            {
                "id": "6896128359923714049",
                "img": "https://tokchart.com/img/6896128359923714049/600",
                "author": "Miley Cyrus",
                "title": "Prisoner (feat. Dua Lipa)",
                "tiktok_url": "https://www.tiktok.com/music/prisoner-feat-dua-lipa-6896128359923714049"
            },
            {
                "id": "6911688776167312134",
                "img": "https://tokchart.com/img/6911688776167312134/600",
                "author": "Gipsy Kings",
                "title": "Bamboleo",
                "tiktok_url": "https://www.tiktok.com/music/bamboleo-6911688776167312134"
            },
            {
                "id": "6878440054709028865",
                "img": "https://tokchart.com/img/6878440054709028865/600",
                "author": "Shawn Mendes",
                "title": "Wonder",
                "tiktok_url": "https://www.tiktok.com/music/wonder-6878440054709028865"
            },
            {
                "id": "6740248251825391617",
                "img": "https://tokchart.com/img/6740248251825391617/600",
                "author": "Labrinth",
                "title": "Forever",
                "tiktok_url": "https://www.tiktok.com/music/forever-6740248251825391617"
            },
            {
                "id": "6889276181086996481",
                "img": "https://tokchart.com/img/6889276181086996481/600",
                "author": "Ariana Grande",
                "title": "pov",
                "tiktok_url": "https://www.tiktok.com/music/pov-6889276181086996481"
            },
            {
                "id": "6886946651135559682",
                "img": "https://tokchart.com/img/6886946651135559682/200",
                "author": "Ariana Grande",
                "title": "positions",
                "tiktok_url": "https://www.tiktok.com/music/positions-6886946651135559682"
            },
            {
                "id": "222453230176251905",
                "img": "https://tokchart.com/img/222453230176251905/200",
                "author": "Natalia Lafourcade",
                "title": "Hasta la Raíz",
                "tiktok_url": "https://www.tiktok.com/music/hasta-la-raiz-222453230176251905"
            },
            {
                "id": "6805761702466947073",
                "img": "https://tokchart.com/img/6805761702466947073/200",
                "author": "Frances Forever",
                "title": "space girl",
                "tiktok_url": "https://www.tiktok.com/music/space-girl-6805761702466947073"
            },
            {
                "id": "6990410706927536902",
                "img": "https://tokchart.com/img/6990410706927536902/200",
                "author": "Tay Money",
                "title": "The Assignment",
                "tiktok_url": "https://www.tiktok.com/music/the-assignment-6990410706927536902"
            },
            {
                "id": "6907566405198841857",
                "img": "https://tokchart.com/img/6907566405198841857/200",
                "author": "Ed Sheeran",
                "title": "Afterglow",
                "tiktok_url": "https://www.tiktok.com/music/afterglow-6907566405198841857"
            }
        ],
        "brazil": [
            {
                "id": "7263298233957354270",
                "img": "https://tokchart.com/img/7263298233957354270/600",
                "author": "FamousSally & YB",
                "title": "Wassup Gway",
                "tiktok_url": "https://www.tiktok.com/music/wassup-gway-7263298233957354270"
            },
            {
                "id": "294017956361990144",
                "img": "https://tokchart.com/img/294017956361990144/600",
                "author": "Soap&Skin",
                "title": "Me and the Devil",
                "tiktok_url": "https://www.tiktok.com/music/me-and-the-devil-294017956361990144"
            },
            {
                "id": "7038873785419712513",
                "img": "https://tokchart.com/img/7038873785419712513/600",
                "author": "Anitta & PEDRO SAMPAIO",
                "title": "NO CHÃO NOVINHA",
                "tiktok_url": "https://www.tiktok.com/music/no-chao-novinha-7038873785419712513"
            },
            {
                "id": "7255087119880816642",
                "img": "https://tokchart.com/img/7255087119880816642/600",
                "author": "Mc Danone & DJ THG & Dj Hm Oliveira",
                "title": "Vem Quebrando",
                "tiktok_url": "https://www.tiktok.com/music/vem-quebrando-7255087119880816642"
            },
            {
                "id": "7266229974662990597",
                "img": "https://tokchart.com/img/7266229974662990597/600",
                "author": "Fabrício Cesar",
                "title": "Eu Nunca nem vi",
                "tiktok_url": "https://www.tiktok.com/music/eu-nunca-nem-vi-7266229974662990597"
            },
            {
                "id": "7039394276502489089",
                "img": "https://tokchart.com/img/7039394276502489089/200",
                "author": "MC Nau",
                "title": "Pisadinha Jingle Bell",
                "tiktok_url": "https://www.tiktok.com/music/pisadinha-jingle-bell-7039394276502489089"
            },
            {
                "id": "7028498814554130433",
                "img": "https://tokchart.com/img/7028498814554130433/200",
                "author": "Anitta",
                "title": "Envolver",
                "tiktok_url": "https://www.tiktok.com/music/envolver-7028498814554130433"
            },
            {
                "id": "7094353534036019974",
                "img": "https://tokchart.com/img/7094353534036019974/200",
                "author": "Mc Paiva ZS & Kotim",
                "title": "Bagulho Louco",
                "tiktok_url": "https://www.tiktok.com/music/bagulho-louco-7094353534036019974"
            },
            {
                "id": "7283236515202665222",
                "img": "https://tokchart.com/img/7283236515202665222/200",
                "author": "Mariana",
                "title": "som original - oxemariana_",
                "tiktok_url": "https://www.tiktok.com/music/som-original-oxemariana-7283236515202665222"
            },
            {
                "id": "7264223716502047493",
                "img": "https://tokchart.com/img/7264223716502047493/200",
                "author": "Mikaela Bisson",
                "title": "original sound - Mikaela Bisson",
                "tiktok_url": "https://www.tiktok.com/music/original-sound-mikaela-bisson-7264223716502047493"
            }
        ],
        "germany": [
            {
                "id": "6967073900530239489",
                "img": "https://tokchart.com/img/6967073900530239489/600",
                "author": "Rocco Hunt & Ana Mena",
                "title": "Un bacio all'improvviso",
                "tiktok_url": "https://www.tiktok.com/music/un-bacio-allimprovviso-6967073900530239489"
            },
            {
                "id": "6988584316469005062",
                "img": "https://tokchart.com/img/6988584316469005062/600",
                "author": "Endzone & Tm",
                "title": "61 Grad",
                "tiktok_url": "https://www.tiktok.com/music/61-grad-6988584316469005062"
            },
            {
                "id": "7071281831944914945",
                "img": "https://tokchart.com/img/7071281831944914945/600",
                "author": "HE/RO",
                "title": "Zu schön um wahr zu sein",
                "tiktok_url": "https://www.tiktok.com/music/zu-schon-um-wahr-zu-sein-7071281831944914945"
            },
            {
                "id": "6974011130414893058",
                "img": "https://tokchart.com/img/6974011130414893058/600",
                "author": "Ed Sheeran",
                "title": "Bad Habits",
                "tiktok_url": "https://www.tiktok.com/music/bad-habits-6974011130414893058"
            },
            {
                "id": "7036343214723090433",
                "img": "https://tokchart.com/img/7036343214723090433/600",
                "author": "AK 33 & SIL3A",
                "title": "Iba3ash",
                "tiktok_url": "https://www.tiktok.com/music/iba3ash-7036343214723090433"
            },
            {
                "id": "6962136464469526530",
                "img": "https://tokchart.com/img/6962136464469526530/200",
                "author": "Milky Chance",
                "title": "Colorado - Main Version",
                "tiktok_url": "https://www.tiktok.com/music/colorado-main-version-6962136464469526530"
            },
            {
                "id": "6812884237704759298",
                "img": "https://tokchart.com/img/6812884237704759298/200",
                "author": "Ali471",
                "title": "GOALGETTER",
                "tiktok_url": "https://www.tiktok.com/music/goalgetter-6812884237704759298"
            },
            {
                "id": "7065267257873532930",
                "img": "https://tokchart.com/img/7065267257873532930/200",
                "author": "Miksu / Macloud & t-low",
                "title": "Sehnsucht",
                "tiktok_url": "https://www.tiktok.com/music/sehnsucht-7065267257873532930"
            },
            {
                "id": "6967274907499497473",
                "img": "https://tokchart.com/img/6967274907499497473/200",
                "author": "Alan Walker & Imanbek",
                "title": "Sweet Dreams",
                "tiktok_url": "https://www.tiktok.com/music/sweet-dreams-6967274907499497473"
            },
            {
                "id": "7055685946238306305",
                "img": "https://tokchart.com/img/7055685946238306305/200",
                "author": "AYLIVA",
                "title": "Schmetterlinge",
                "tiktok_url": "https://www.tiktok.com/music/schmetterlinge-7055685946238306305"
            }
        ],
        "france": [
            {
                "id": "7075729123557100294",
                "img": "https://tokchart.com/img/7075729123557100294/600",
                "author": "Duke & Jones & Louis Theroux",
                "title": "Jiggle Jiggle",
                "tiktok_url": "https://www.tiktok.com/music/jiggle-jiggle-7075729123557100294"
            },
            {
                "id": "7083553230642449157",
                "img": "https://tokchart.com/img/7083553230642449157/600",
                "author": "Tayc",
                "title": "Sans effet",
                "tiktok_url": "https://www.tiktok.com/music/sans-effet-7083553230642449157"
            },
            {
                "id": "6959038898324375554",
                "img": "https://tokchart.com/img/6959038898324375554/600",
                "author": "Diego",
                "title": "Faut pas abuser",
                "tiktok_url": "https://www.tiktok.com/music/faut-pas-abuser-6959038898324375554"
            },
            {
                "id": "7069404184566663941",
                "img": "https://tokchart.com/img/7069404184566663941/600",
                "author": "Gambino La MG",
                "title": "Reste-là (feat. Tiakola)",
                "tiktok_url": "https://www.tiktok.com/music/reste-la-feat-tiakola-7069404184566663941"
            },
            {
                "id": "7029514292927924226",
                "img": "https://tokchart.com/img/7029514292927924226/600",
                "author": "Eva",
                "title": "Ciel",
                "tiktok_url": "https://www.tiktok.com/music/ciel-7029514292927924226"
            },
            {
                "id": "7039374467587476230",
                "img": "https://tokchart.com/img/7039374467587476230/200",
                "author": "Niska",
                "title": "T-Rain",
                "tiktok_url": "https://www.tiktok.com/music/t-rain-7039374467587476230"
            },
            {
                "id": "6981876115275057153",
                "img": "https://tokchart.com/img/6981876115275057153/200",
                "author": "Livaï",
                "title": "Nous deux c'est mieux <3",
                "tiktok_url": "https://www.tiktok.com/music/nous-deux-cest-mieux-3-6981876115275057153"
            },
            {
                "id": "6926602705243506689",
                "img": "https://tokchart.com/img/6926602705243506689/200",
                "author": "Tayc",
                "title": "Ma Bonnie",
                "tiktok_url": "https://www.tiktok.com/music/ma-bonnie-6926602705243506689"
            },
            {
                "id": "7030087596596398853",
                "img": "https://tokchart.com/img/7030087596596398853/200",
                "author": "Gambi",
                "title": "Khedma",
                "tiktok_url": "https://www.tiktok.com/music/khedma-7030087596596398853"
            },
            {
                "id": "6929156272663054337",
                "img": "https://tokchart.com/img/6929156272663054337/200",
                "author": "La Femme",
                "title": "Elle ne t'aime pas",
                "tiktok_url": "https://www.tiktok.com/music/elle-ne-taime-pas-6929156272663054337"
            }
        ],
        "mexico": [
            {
                "id": "6970120467705236230",
                "img": "https://tokchart.com/img/6970120467705236230/600",
                "author": "Fuego",
                "title": "Una Vaina Loca",
                "tiktok_url": "https://www.tiktok.com/music/una-vaina-loca-6970120467705236230"
            },
            {
                "id": "7022765400865655557",
                "img": "https://tokchart.com/img/7022765400865655557/600",
                "author": "zzoilo & Aitana",
                "title": "Mon Amour - Remix",
                "tiktok_url": "https://www.tiktok.com/music/mon-amour-remix-7022765400865655557"
            },
            {
                "id": "6948076402331617281",
                "img": "https://tokchart.com/img/6948076402331617281/600",
                "author": "Carlos Vives & Ricky Martin",
                "title": "Canción Bonita",
                "tiktok_url": "https://www.tiktok.com/music/cancion-bonita-6948076402331617281"
            },
            {
                "id": "7186137741745195822",
                "img": "https://tokchart.com/img/7186137741745195822/600",
                "author": "Oscar Maydan",
                "title": "Fin De Semana",
                "tiktok_url": "https://www.tiktok.com/music/fin-de-semana-7186137741745195822"
            },
            {
                "id": "7187816271247853569",
                "img": "https://tokchart.com/img/7187816271247853569/600",
                "author": "Miley Cyrus",
                "title": "Flowers",
                "tiktok_url": "https://www.tiktok.com/music/flowers-7187816271247853569"
            },
            {
                "id": "6724612380384299010",
                "img": "https://tokchart.com/img/6724612380384299010/200",
                "author": "Chiquetere Band",
                "title": "Chiquetere",
                "tiktok_url": "https://www.tiktok.com/music/chiquetere-6724612380384299010"
            },
            {
                "id": "7132977053581707266",
                "img": "https://tokchart.com/img/7132977053581707266/200",
                "author": "Feid",
                "title": "Feliz Cumpleaños Ferxxo",
                "tiktok_url": "https://www.tiktok.com/music/feliz-cumpleanos-ferxxo-7132977053581707266"
            },
            {
                "id": "6964598276440066822",
                "img": "https://tokchart.com/img/6964598276440066822/200",
                "author": "Osmani Garcia \"La Voz\" & Pitbull & Sensato & Dayami La Musa",
                "title": "El Taxi - Extended Mix",
                "tiktok_url": "https://www.tiktok.com/music/el-taxi-extended-mix-6964598276440066822"
            },
            {
                "id": "7095407294631987973",
                "img": "https://tokchart.com/img/7095407294631987973/200",
                "author": "Bad Bunny & Chencho Corleone",
                "title": "Me Porto Bonito",
                "tiktok_url": "https://www.tiktok.com/music/me-porto-bonito-7095407294631987973"
            },
            {
                "id": "7088058267955366661",
                "img": "https://tokchart.com/img/7088058267955366661/200",
                "author": "Don Chezina",
                "title": "Vacilon",
                "tiktok_url": "https://www.tiktok.com/music/vacilon-7088058267955366661"
            }
        ]
    }
}